MANIFEST.in
README.md
setup.py
janeliasig/__init__.py
janeliasig/algorithm.py
janeliasig/gui_browser.py
janeliasig/test_janeliasig.py
janeliasig.egg-info/PKG-INFO
janeliasig.egg-info/SOURCES.txt
janeliasig.egg-info/dependency_links.txt
janeliasig.egg-info/not-zip-safe
janeliasig.egg-info/requires.txt
janeliasig.egg-info/top_level.txt