Metadata-Version: 1.1
Name: janeliasig
Version: 0.94
Summary: Rudimentary Simulations/Manipulations of PMT Outputs
Home-page: http://github.com/SpenceyHong/janeliasig
Author: Spencer Hong
Author-email: spencer.hongx@gmail.com
License: MIT
Platform: UNKNOWN
Classifier: Development Status :: 3 - Alpha
Classifier: License :: OSI Approved :: MIT License
Classifier: Natural Language :: English
Classifier: Programming Language :: Python :: 2.7
Classifier: Topic :: Scientific/Engineering :: Information Analysis
